readyview/__init__.py
readyview/config.py
readyview/dashboard.py
readyview/network.py
readyview/rest_session.py
readyview/switch.py
readyview-1.8.0.dist-info/METADATA
readyview-1.8.0.dist-info/WHEEL
readyview-1.8.0.dist-info/licenses/LICENSE
readyview-1.8.0.dist-info/RECORD
