Metadata-Version: 2.4
Name: readyview
Version: 1.8.0
Summary: ReadyLinks ReadyView API library.
Project-URL: Homepage, https://gitlab.com/readylinks
Project-URL: Issues, https://gitlab.com/readylinks
Author-email: ReadyLinks Developers <developers@ready-links.com>
License-File: LICENSE
Classifier: License :: OSI Approved :: MIT License
Classifier: Operating System :: OS Independent
Classifier: Programming Language :: Python :: 3
Requires-Python: >=3.8
Requires-Dist: requests
